MANIFEST.in
README.txt
setup.py
src/setupbuilder/__init__.py
src/setupbuilder.egg-info/PKG-INFO
src/setupbuilder.egg-info/SOURCES.txt
src/setupbuilder.egg-info/dependency_links.txt
src/setupbuilder.egg-info/entry_points.txt
src/setupbuilder.egg-info/requires.txt
src/setupbuilder.egg-info/top_level.txt