Metadata-Version: 1.0
Name: setupbuilder
Version: 0.0.1
Summary: Command to generate setup for python packages.
Home-page: http://pypi.python.org/setupbuilder
Author: Rodrigo Pinheiro Matias
Author-email: rodrigopmatias@gmail.com
License: GPLv3
Platform: linux
Platform: linux2
Platform: osx
Platform: win32
Platform: win64
